{
  "classifier": {
    "brain": {
      "layers": [
        {
          "0": {},
          "1": {},
          "2": {},
          "3": {},
          "4": {},
          "5": {},
          "6": {},
          "7": {},
          "8": {},
          "9": {},
          "10": {},
          "11": {}
        },
        {
          "0": {
            "bias": -0.6346330456736943,
            "weights": {
              "0": 0.5984331314681118,
              "1": -0.875121077460762,
              "2": -1.1794378414798505,
              "3": 0.12216236684709322,
              "4": -0.06140074965903663,
              "5": -0.03052929521475826,
              "6": 2.212704168628191,
              "7": 2.7014766954706873,
              "8": 2.0615376833515446,
              "9": -0.029287185880038674,
              "10": -4.5699515953317835,
              "11": -2.947075847112379
            }
          },
          "1": {
            "bias": -0.31793156272073525,
            "weights": {
              "0": -0.5590721742467509,
              "1": -0.021595381212073602,
              "2": -3.2018807706528447,
              "3": -0.7136887623494507,
              "4": -0.26794894428162713,
              "5": 0.024246860430301758,
              "6": 2.0328036802743936,
              "7": 3.9528878130566185,
              "8": 0.4175659842548865,
              "9": 3.7916851471855404,
              "10": 2.188782037751085,
              "11": 4.651331022702601
            }
          },
          "2": {
            "bias": 0.3698763237109897,
            "weights": {
              "0": -0.3885751550225956,
              "1": 0.309278379430528,
              "2": 0.28160987513269703,
              "3": 0.9989808519023528,
              "4": 0.16930160389500656,
              "5": 0.35077509051003186,
              "6": -3.869155243318514,
              "7": -5.467585283013971,
              "8": -0.9606995847372501,
              "9": -1.3032975890151957,
              "10": 0.05774161130552822,
              "11": 0.43351580079183016
            }
          },
          "3": {
            "bias": -0.022705132275418805,
            "weights": {
              "0": 0.7636165833179231,
              "1": -0.5050945823136408,
              "2": 4.831534907290416,
              "3": 1.5199614449537233,
              "4": 0.19536372466478147,
              "5": 0.18836335906045285,
              "6": -2.9631085197581295,
              "7": -2.6898640086152383,
              "8": -2.7245330952010667,
              "9": -3.5679953462357346,
              "10": 2.041283587079436,
              "11": -4.436203832919341
            }
          },
          "4": {
            "bias": 0.45746787083320667,
            "weights": {
              "0": 1.398776348503678,
              "1": 0.34805001709367617,
              "2": 3.322291440834778,
              "3": 1.0115548609079936,
              "4": 0.23789542523359258,
              "5": 0.18678224267643195,
              "6": 0.09935955329984315,
              "7": -0.5610019888732241,
              "8": 0.5177631744474769,
              "9": -4.660780735829283,
              "10": -3.9888054658100716,
              "11": -5.165432041651567
            }
          },
          "5": {
            "bias": 0.9520118301964028,
            "weights": {
              "0": -0.3663414383119602,
              "1": 0.5567856784103913,
              "2": 0.0017655053670294655,
              "3": 0.8289920688306769,
              "4": 0.032575224972546744,
              "5": 0.3152195864213736,
              "6": -2.9472377884212175,
              "7": -4.507553704761189,
              "8": -0.8295298502335738,
              "9": 2.431316521834557,
              "10": -0.17141256080270453,
              "11": -3.29306169783065
            }
          }
        },
        {
          "makeAppointment": {
            "bias": -2.927152233168131,
            "weights": {
              "0": -2.0143847865706723,
              "1": -5.337289392511223,
              "2": 4.248778879885703,
              "3": 2.6501653861158885,
              "4": 1.9859140726031612,
              "5": 6.348104445538641
            }
          },
          "changeAppointment": {
            "bias": -0.19682394720656593,
            "weights": {
              "0": 5.5688646998496045,
              "1": -0.34805393113631644,
              "2": -5.691225044372166,
              "3": -4.930065212975785,
              "4": 2.26098918655888,
              "5": -4.2778562289995055
            }
          },
          "getApptCount": {
            "bias": -0.46355368953240467,
            "weights": {
              "0": -2.5720915847740105,
              "1": 1.6533913085591458,
              "2": 4.169105710518262,
              "3": -4.791898235556583,
              "4": -6.080840220577551,
              "5": -1.2986807233795525
            }
          },
          "changeAppt": {
            "bias": -1.0438087990864322,
            "weights": {
              "0": -5.966612888614031,
              "1": 1.8741947381267343,
              "2": -6.078917690072851,
              "3": 4.430663794842504,
              "4": -1.6044685358142512,
              "5": -4.203637223613712
            }
          }
        }
      ],
      "outputLookup": true,
      "inputLookup": false
    },
    "data": [
      {
        "input": [
          1,
          1,
          0,
          0,
          0,
          0,
          0,
          0,
          0,
          0,
          0,
          0
        ],
        "output": {
          "makeAppointment": 1
        }
      },
      {
        "input": [
          0,
          1,
          0,
          0,
          0,
          0,
          0,
          0,
          0,
          0,
          0,
          0
        ],
        "output": {
          "makeAppointment": 1
        }
      },
      {
        "input": [
          0,
          0,
          1,
          1,
          1,
          1,
          0,
          0,
          0,
          0,
          0,
          0
        ],
        "output": {
          "makeAppointment": 1
        }
      },
      {
        "input": [
          1,
          1,
          0,
          1,
          0,
          0,
          0,
          0,
          0,
          0,
          0,
          0
        ],
        "output": {
          "makeAppointment": 1
        }
      },
      {
        "input": [
          0,
          1,
          0,
          1,
          0,
          0,
          0,
          0,
          0,
          0,
          0,
          0
        ],
        "output": {
          "makeAppointment": 1
        }
      },
      {
        "input": [
          1,
          1,
          0,
          0,
          0,
          0,
          1,
          0,
          0,
          0,
          0,
          0
        ],
        "output": {
          "changeAppointment": 1
        }
      },
      {
        "input": [
          0,
          1,
          0,
          0,
          0,
          0,
          0,
          1,
          0,
          0,
          0,
          0
        ],
        "output": {
          "changeAppointment": 1
        }
      },
      {
        "input": [
          0,
          1,
          1,
          0,
          0,
          0,
          0,
          1,
          1,
          0,
          0,
          0
        ],
        "output": {
          "changeAppointment": 1
        }
      },
      {
        "input": [
          0,
          1,
          0,
          0,
          0,
          0,
          0,
          0,
          0,
          1,
          0,
          0
        ],
        "output": {
          "getApptCount": 1
        }
      },
      {
        "input": [
          0,
          1,
          0,
          0,
          0,
          0,
          0,
          0,
          0,
          1,
          0,
          0
        ],
        "output": {
          "getApptCount": 1
        }
      },
      {
        "input": [
          0,
          1,
          0,
          0,
          0,
          0,
          0,
          0,
          0,
          1,
          0,
          0
        ],
        "output": {
          "makeAppointment": 1
        }
      },
      {
        "input": [
          0,
          1,
          1,
          0,
          0,
          0,
          0,
          0,
          0,
          1,
          0,
          0
        ],
        "output": {
          "makeAppointment": 1
        }
      },
      {
        "input": [
          0,
          1,
          1,
          0,
          0,
          0,
          0,
          0,
          0,
          0,
          1,
          0
        ],
        "output": {
          "makeAppointment": 1
        }
      },
      {
        "input": [
          0,
          1,
          0,
          0,
          0,
          0,
          0,
          0,
          0,
          0,
          0,
          1
        ],
        "output": {
          "getApptCount": 1
        }
      },
      {
        "input": [
          0,
          1,
          1,
          0,
          0,
          0,
          0,
          1,
          0,
          0,
          1,
          0
        ],
        "output": {
          "changeAppt": 1
        }
      }
    ]
  },
  "docs": [
    {
      "label": "makeAppointment",
      "text": [
        "need",
        "appoint"
      ]
    },
    {
      "label": "makeAppointment",
      "text": [
        "appoint"
      ]
    },
    {
      "label": "makeAppointment",
      "text": [
        "want",
        "schedul",
        "appt",
        "john"
      ]
    },
    {
      "label": "makeAppointment",
      "text": [
        "need",
        "schedul",
        "appoint"
      ]
    },
    {
      "label": "makeAppointment",
      "text": [
        "schedul",
        "appoint"
      ]
    },
    {
      "label": "changeAppointment",
      "text": [
        "need",
        "reschedul",
        "appoint"
      ]
    },
    {
      "label": "changeAppointment",
      "text": [
        "chang",
        "appoint"
      ]
    },
    {
      "label": "changeAppointment",
      "text": [
        "want",
        "chang",
        "appoint",
        "bob"
      ]
    },
    {
      "label": "getApptCount",
      "text": [
        "appoint",
        "todai"
      ]
    },
    {
      "label": "getApptCount",
      "text": [
        "appoint",
        "todai"
      ]
    },
    {
      "label": "makeAppointment",
      "text": [
        "appoint",
        "todai"
      ]
    },
    {
      "label": "makeAppointment",
      "text": [
        "want",
        "appoint",
        "todai"
      ]
    },
    {
      "label": "makeAppointment",
      "text": [
        "want",
        "appoint",
        "tuesdai"
      ]
    },
    {
      "label": "getApptCount",
      "text": [
        "when",
        "appoint"
      ]
    },
    {
      "label": "changeAppt",
      "text": [
        "want",
        "chang",
        "appoint",
        "tuesdai"
      ]
    }
  ],
  "features": {
    "need": 3,
    "appoint": 14,
    "want": 5,
    "schedul": 3,
    "appt": 1,
    "john": 1,
    "reschedul": 1,
    "chang": 3,
    "bob": 1,
    "todai": 4,
    "tuesdai": 2,
    "when": 1
  },
  "stemmer": {},
  "lastAdded": 15,
  "events": {
    "domain": null,
    "_events": {},
    "_eventsCount": 0
  }
}
